tencentcloud/__init__.py
tencentcloud/es/__init__.py
tencentcloud/es/v20180416/__init__.py
tencentcloud/es/v20180416/errorcodes.py
tencentcloud/es/v20180416/es_client.py
tencentcloud/es/v20180416/es_client_async.py
tencentcloud/es/v20180416/models.py
tencentcloud/es/v20250101/__init__.py
tencentcloud/es/v20250101/errorcodes.py
tencentcloud/es/v20250101/es_client.py
tencentcloud/es/v20250101/es_client_async.py
tencentcloud/es/v20250101/models.py
tencentcloud_sdk_python_es-3.1.22.dist-info/METADATA
tencentcloud_sdk_python_es-3.1.22.dist-info/WHEEL
tencentcloud_sdk_python_es-3.1.22.dist-info/top_level.txt
tencentcloud_sdk_python_es-3.1.22.dist-info/RECORD
